epicbot_images/__init__.py
epicbot_images/effects.py
epicbot_images/memes.py
epicbot_images/utils.py
epicbot_images/assets/fonts/Roboto-Bold.ttf
epicbot_images/assets/meme_templates/bernie.png
epicbot_images/assets/meme_templates/disappointed.png
epicbot_images/assets/meme_templates/doge.png
epicbot_images/assets/meme_templates/drake.png
epicbot_images/assets/meme_templates/flex_tape.png
epicbot_images/assets/meme_templates/my_heart.png
epicbot_images/assets/meme_templates/panik.png
epicbot_images/temp/bernie.png
epicbot_images/temp/blur.png
epicbot_images/temp/disappointed.png
epicbot_images/temp/doge.png
epicbot_images/temp/drake.png
epicbot_images/temp/enhance.png
epicbot_images/temp/flex_tape.png
epicbot_images/temp/flip.png
epicbot_images/temp/my_heart.png
epicbot_images/temp/panik.png
epicbot_images/temp/wiggle.gif
epicbot_images-1.8.dist-info/LICENSE
epicbot_images-1.8.dist-info/METADATA
epicbot_images-1.8.dist-info/WHEEL
epicbot_images-1.8.dist-info/top_level.txt
epicbot_images-1.8.dist-info/RECORD
