Metadata-Version: 2.1
Name: epicbot-images
Version: 1.8
Summary: An image manipulation module for EpicBot.
Home-page: https://github.com/Nirlep5252/epicbot-images
Author: Nirlep_5252_
License: MIT
Keywords: discord.py,meme,discord,image-gen
Platform: UNKNOWN
Requires-Python: >=3.5.3
License-File: LICENSE
Requires-Dist: pillow (>=8.1.2)
Requires-Dist: wand (>=0.6.6)
Requires-Dist: numpy (>=1.21.1)
